dsplayer_soundcloud/__init__.py
dsplayer_soundcloud/soundcloud.py
plugin/__init__.py
plugin/plugin.py
dsplayer_soundcloud-1.3.0.dist-info/LICENSE
dsplayer_soundcloud-1.3.0.dist-info/METADATA
dsplayer_soundcloud-1.3.0.dist-info/WHEEL
dsplayer_soundcloud-1.3.0.dist-info/entry_points.txt
dsplayer_soundcloud-1.3.0.dist-info/top_level.txt
dsplayer_soundcloud-1.3.0.dist-info/RECORD
